sortout/__init__.py
sortout/test.py
sortout-0.1.0.dist-info/LICENSE
sortout-0.1.0.dist-info/METADATA
sortout-0.1.0.dist-info/WHEEL
sortout-0.1.0.dist-info/top_level.txt
sortout-0.1.0.dist-info/RECORD
