Metadata-Version: 2.1
Name: sortout
Version: 0.1.0
Summary: An integrative library that contains tools for using various types of sorting algorithms to work together.
Home-page: https://github.com/yogesh-aggarwal/sortout
Author: Yogesh Aggarwal
Author-email: developeryogeshgit@gmail.com
License: AGPL 3.0
Download-URL: https://github.com/yogesh-aggarwal/sortout/blob/master/dist/sortout-0.1.0.tar.gz
Keywords: SORTING,MULTIPLE SORTS,ALGORITHMS
Platform: UNKNOWN
Classifier: Development Status :: 3 - Alpha
Classifier: Intended Audience :: Developers
Classifier: Programming Language :: Python :: 3
Classifier: Programming Language :: Python :: 3.4
Classifier: Programming Language :: Python :: 3.5
Classifier: Programming Language :: Python :: 3.6
Classifier: Programming Language :: Python :: 3.7
